incontinuity/__init__.py
incontinuity-0.0.0.dist-info/LICENSE
incontinuity-0.0.0.dist-info/METADATA
incontinuity-0.0.0.dist-info/WHEEL
incontinuity-0.0.0.dist-info/RECORD
