Metadata-Version: 2.1
Name: incontinuity
Version: 0.0.0
Summary: Context control for LLM inference on a per-token basis
Home-page: https://github.com/lukejagg/incontinuity
Keywords: llm,llm agent,prompt,ai
Author: Lucas Jaggernauth
Author-email: lukejagg@gmail.com
Requires-Python: >=3.8,<4.0
Classifier: Intended Audience :: Developers
Classifier: License :: OSI Approved :: MIT License
Classifier: Programming Language :: Python :: 3
Classifier: Programming Language :: Python :: 3.8
Classifier: Programming Language :: Python :: 3.9
Classifier: Programming Language :: Python :: 3.10
Classifier: Programming Language :: Python :: 3.11
Classifier: Programming Language :: Python :: 3.12
Project-URL: Bug Tracker, https://github.com/lukejagg/incontinuity/issues
Project-URL: Repository, https://github.com/lukejagg/incontinuity
